[
  {
    "line": 7,
    "elements": [
      {
        "start_timestamp": "2023-03-26T21:19:24.815Z",
        "line": 11,
        "name": "Title of your scenario",
        "description": "",
        "id": "validate-text-colour-with-hexa-value;title-of-your-scenario",
        "after": [
          {
            "result": {
              "error_message": "org.picocontainer.injectors.AbstractInjector$UnsatisfiableDependenciesException: StepDefinition_Files.ScreenshotStepDefs has unsatisfied dependency \u0027interface org.openqa.selenium.WebDriver\u0027 for constructor \u0027public StepDefinition_Files.ScreenshotStepDefs(org.openqa.selenium.WebDriver)\u0027 from org.picocontainer.DefaultPicoContainer@514de325:5\u003c|\r\n\tat org.picocontainer.injectors.ConstructorInjector.getGreediestSatisfiableConstructor(ConstructorInjector.java:191)\r\n\tat org.picocontainer.injectors.ConstructorInjector.getGreediestSatisfiableConstructor(ConstructorInjector.java:110)\r\n\tat org.picocontainer.injectors.ConstructorInjector.access$100(ConstructorInjector.java:51)\r\n\tat org.picocontainer.injectors.ConstructorInjector$1.run(ConstructorInjector.java:331)\r\n\tat org.picocontainer.injectors.AbstractInjector$ThreadLocalCyclicDependencyGuard.observe(AbstractInjector.java:270)\r\n\tat org.picocontainer.injectors.ConstructorInjector.getComponentInstance(ConstructorInjector.java:364)\r\n\tat org.picocontainer.injectors.AbstractInjectionFactory$LifecycleAdapter.getComponentInstance(AbstractInjectionFactory.java:56)\r\n\tat org.picocontainer.behaviors.AbstractBehavior.getComponentInstance(AbstractBehavior.java:64)\r\n\tat org.picocontainer.behaviors.Stored.getComponentInstance(Stored.java:91)\r\n\tat org.picocontainer.DefaultPicoContainer.getInstance(DefaultPicoContainer.java:699)\r\n\tat org.picocontainer.DefaultPicoContainer.getComponent(DefaultPicoContainer.java:647)\r\n\tat org.picocontainer.DefaultPicoContainer.getComponent(DefaultPicoContainer.java:678)\r\n\tat io.cucumber.picocontainer.PicoFactory.getInstance(PicoFactory.java:47)\r\n\tat io.cucumber.java.AbstractGlueDefinition.invokeMethod(AbstractGlueDefinition.java:47)\r\n\tat io.cucumber.java.JavaHookDefinition.execute(JavaHookDefinition.java:59)\r\n\tat io.cucumber.core.runner.CoreHookDefinition.execute(CoreHookDefinition.java:46)\r\n\tat io.cucumber.core.runner.HookDefinitionMatch.runStep(HookDefinitionMatch.java:21)\r\n\tat io.cucumber.core.runner.ExecutionMode$1.execute(ExecutionMode.java:10)\r\n\tat io.cucumber.core.runner.TestStep.executeStep(TestStep.java:92)\r\n\tat io.cucumber.core.runner.TestStep.run(TestStep.java:64)\r\n\tat io.cucumber.core.runner.TestCase.run(TestCase.java:110)\r\n\tat io.cucumber.core.runner.Runner.runPickle(Runner.java:73)\r\n\tat io.cucumber.junit.PickleRunners$NoStepDescriptions.run(PickleRunners.java:151)\r\n\tat io.cucumber.junit.FeatureRunner.runChild(FeatureRunner.java:135)\r\n\tat io.cucumber.junit.FeatureRunner.runChild(FeatureRunner.java:27)\r\n\tat org.junit.runners.ParentRunner$3.run(ParentRunner.java:238)\r\n\tat org.junit.runners.ParentRunner$1.schedule(ParentRunner.java:63)\r\n\tat org.junit.runners.ParentRunner.runChildren(ParentRunner.java:236)\r\n\tat org.junit.runners.ParentRunner.access$000(ParentRunner.java:53)\r\n\tat org.junit.runners.ParentRunner$2.evaluate(ParentRunner.java:229)\r\n\tat org.junit.runners.ParentRunner.run(ParentRunner.java:309)\r\n\tat io.cucumber.junit.Cucumber.runChild(Cucumber.java:200)\r\n\tat io.cucumber.junit.Cucumber.runChild(Cucumber.java:90)\r\n\tat org.junit.runners.ParentRunner$3.run(ParentRunner.java:238)\r\n\tat org.junit.runners.ParentRunner$1.schedule(ParentRunner.java:63)\r\n\tat org.junit.runners.ParentRunner.runChildren(ParentRunner.java:236)\r\n\tat org.junit.runners.ParentRunner.access$000(ParentRunner.java:53)\r\n\tat org.junit.runners.ParentRunner$2.evaluate(ParentRunner.java:229)\r\n\tat io.cucumber.junit.Cucumber$RunCucumber.evaluate(Cucumber.java:235)\r\n\tat org.junit.runners.ParentRunner.run(ParentRunner.java:309)\r\n\tat org.eclipse.jdt.internal.junit4.runner.JUnit4TestReference.run(JUnit4TestReference.java:93)\r\n\tat org.eclipse.jdt.internal.junit.runner.TestExecution.run(TestExecution.java:40)\r\n\tat org.eclipse.jdt.internal.junit.runner.RemoteTestRunner.runTests(RemoteTestRunner.java:529)\r\n\tat org.eclipse.jdt.internal.junit.runner.RemoteTestRunner.runTests(RemoteTestRunner.java:756)\r\n\tat org.eclipse.jdt.internal.junit.runner.RemoteTestRunner.run(RemoteTestRunner.java:452)\r\n\tat org.eclipse.jdt.internal.junit.runner.RemoteTestRunner.main(RemoteTestRunner.java:210)\r\n",
              "duration": 2995600,
              "status": "failed"
            },
            "match": {
              "location": "StepDefinition_Files.ScreenshotStepDefs.afterScenario(io.cucumber.java.Scenario)"
            }
          }
        ],
        "type": "scenario",
        "keyword": "Scenario",
        "steps": [
          {
            "result": {
              "duration": 7482211100,
              "status": "passed"
            },
            "line": 12,
            "name": "I launch URl",
            "match": {
              "location": "StepDefinition_Files.CSS_Value_validate_Colour.i_launch_u_rl()"
            },
            "keyword": "Given "
          },
          {
            "result": {
              "duration": 6823770300,
              "status": "passed"
            },
            "line": 13,
            "name": "I validate the color of text",
            "match": {
              "location": "StepDefinition_Files.CSS_Value_validate_Colour.i_take_rgb_value()"
            },
            "keyword": "Then "
          }
        ],
        "tags": [
          {
            "name": "@Validate_ColurOf_Text"
          },
          {
            "name": "@Validate_with_hexaValue"
          }
        ]
      }
    ],
    "name": "Validate Text Colour with hexa value",
    "description": "",
    "id": "validate-text-colour-with-hexa-value",
    "keyword": "Feature",
    "uri": "file:src/test/resources/Cucumber/CSS_Value_validate_Colour.feature",
    "tags": [
      {
        "name": "@Validate_ColurOf_Text",
        "type": "Tag",
        "location": {
          "line": 6,
          "column": 1
        }
      }
    ]
  },
  {
    "line": 5,
    "elements": [
      {
        "start_timestamp": "2023-03-26T21:19:39.344Z",
        "line": 9,
        "name": "Amazon Auto search",
        "description": "",
        "id": "dropdown-options;amazon-auto-search",
        "after": [
          {
            "result": {
              "error_message": "org.picocontainer.injectors.AbstractInjector$UnsatisfiableDependenciesException: StepDefinition_Files.ScreenshotStepDefs has unsatisfied dependency \u0027interface org.openqa.selenium.WebDriver\u0027 for constructor \u0027public StepDefinition_Files.ScreenshotStepDefs(org.openqa.selenium.WebDriver)\u0027 from org.picocontainer.DefaultPicoContainer@5dc0ff7d:5\u003c|\r\n\tat org.picocontainer.injectors.ConstructorInjector.getGreediestSatisfiableConstructor(ConstructorInjector.java:191)\r\n\tat org.picocontainer.injectors.ConstructorInjector.getGreediestSatisfiableConstructor(ConstructorInjector.java:110)\r\n\tat org.picocontainer.injectors.ConstructorInjector.access$100(ConstructorInjector.java:51)\r\n\tat org.picocontainer.injectors.ConstructorInjector$1.run(ConstructorInjector.java:331)\r\n\tat org.picocontainer.injectors.AbstractInjector$ThreadLocalCyclicDependencyGuard.observe(AbstractInjector.java:270)\r\n\tat org.picocontainer.injectors.ConstructorInjector.getComponentInstance(ConstructorInjector.java:364)\r\n\tat org.picocontainer.injectors.AbstractInjectionFactory$LifecycleAdapter.getComponentInstance(AbstractInjectionFactory.java:56)\r\n\tat org.picocontainer.behaviors.AbstractBehavior.getComponentInstance(AbstractBehavior.java:64)\r\n\tat org.picocontainer.behaviors.Stored.getComponentInstance(Stored.java:91)\r\n\tat org.picocontainer.DefaultPicoContainer.getInstance(DefaultPicoContainer.java:699)\r\n\tat org.picocontainer.DefaultPicoContainer.getComponent(DefaultPicoContainer.java:647)\r\n\tat org.picocontainer.DefaultPicoContainer.getComponent(DefaultPicoContainer.java:678)\r\n\tat io.cucumber.picocontainer.PicoFactory.getInstance(PicoFactory.java:47)\r\n\tat io.cucumber.java.AbstractGlueDefinition.invokeMethod(AbstractGlueDefinition.java:47)\r\n\tat io.cucumber.java.JavaHookDefinition.execute(JavaHookDefinition.java:59)\r\n\tat io.cucumber.core.runner.CoreHookDefinition.execute(CoreHookDefinition.java:46)\r\n\tat io.cucumber.core.runner.HookDefinitionMatch.runStep(HookDefinitionMatch.java:21)\r\n\tat io.cucumber.core.runner.ExecutionMode$1.execute(ExecutionMode.java:10)\r\n\tat io.cucumber.core.runner.TestStep.executeStep(TestStep.java:92)\r\n\tat io.cucumber.core.runner.TestStep.run(TestStep.java:64)\r\n\tat io.cucumber.core.runner.TestCase.run(TestCase.java:110)\r\n\tat io.cucumber.core.runner.Runner.runPickle(Runner.java:73)\r\n\tat io.cucumber.junit.PickleRunners$NoStepDescriptions.run(PickleRunners.java:151)\r\n\tat io.cucumber.junit.FeatureRunner.runChild(FeatureRunner.java:135)\r\n\tat io.cucumber.junit.FeatureRunner.runChild(FeatureRunner.java:27)\r\n\tat org.junit.runners.ParentRunner$3.run(ParentRunner.java:238)\r\n\tat org.junit.runners.ParentRunner$1.schedule(ParentRunner.java:63)\r\n\tat org.junit.runners.ParentRunner.runChildren(ParentRunner.java:236)\r\n\tat org.junit.runners.ParentRunner.access$000(ParentRunner.java:53)\r\n\tat org.junit.runners.ParentRunner$2.evaluate(ParentRunner.java:229)\r\n\tat org.junit.runners.ParentRunner.run(ParentRunner.java:309)\r\n\tat io.cucumber.junit.Cucumber.runChild(Cucumber.java:200)\r\n\tat io.cucumber.junit.Cucumber.runChild(Cucumber.java:90)\r\n\tat org.junit.runners.ParentRunner$3.run(ParentRunner.java:238)\r\n\tat org.junit.runners.ParentRunner$1.schedule(ParentRunner.java:63)\r\n\tat org.junit.runners.ParentRunner.runChildren(ParentRunner.java:236)\r\n\tat org.junit.runners.ParentRunner.access$000(ParentRunner.java:53)\r\n\tat org.junit.runners.ParentRunner$2.evaluate(ParentRunner.java:229)\r\n\tat io.cucumber.junit.Cucumber$RunCucumber.evaluate(Cucumber.java:235)\r\n\tat org.junit.runners.ParentRunner.run(ParentRunner.java:309)\r\n\tat org.eclipse.jdt.internal.junit4.runner.JUnit4TestReference.run(JUnit4TestReference.java:93)\r\n\tat org.eclipse.jdt.internal.junit.runner.TestExecution.run(TestExecution.java:40)\r\n\tat org.eclipse.jdt.internal.junit.runner.RemoteTestRunner.runTests(RemoteTestRunner.java:529)\r\n\tat org.eclipse.jdt.internal.junit.runner.RemoteTestRunner.runTests(RemoteTestRunner.java:756)\r\n\tat org.eclipse.jdt.internal.junit.runner.RemoteTestRunner.run(RemoteTestRunner.java:452)\r\n\tat org.eclipse.jdt.internal.junit.runner.RemoteTestRunner.main(RemoteTestRunner.java:210)\r\n",
              "duration": 12508300,
              "status": "failed"
            },
            "match": {
              "location": "StepDefinition_Files.ScreenshotStepDefs.afterScenario(io.cucumber.java.Scenario)"
            }
          }
        ],
        "type": "scenario",
        "keyword": "Scenario",
        "steps": [
          {
            "result": {
              "duration": 3872944200,
              "status": "passed"
            },
            "line": 10,
            "name": "when i launch chrome browser",
            "match": {
              "location": "StepDefinition_Files.DropDown.when_i_launch_chrome_browser()"
            },
            "keyword": "Given "
          },
          {
            "result": {
              "duration": 6403426100,
              "status": "passed"
            },
            "line": 11,
            "name": "I enter URL",
            "match": {
              "location": "StepDefinition_Files.DropDown.i_enter_url()"
            },
            "keyword": "Then "
          },
          {
            "result": {
              "duration": 11780009400,
              "status": "passed"
            },
            "line": 12,
            "name": "enter credential in Amazon serach bar \"Recliner for kids\"",
            "match": {
              "arguments": [
                {
                  "val": "\"Recliner for kids\"",
                  "offset": 38
                }
              ],
              "location": "StepDefinition_Files.DropDown.enter_credential_in_amazon_serach_bar(java.lang.String)"
            },
            "keyword": "And "
          },
          {
            "result": {
              "duration": 1492612400,
              "status": "passed"
            },
            "line": 13,
            "name": "Recliner for kids gets displayed",
            "match": {
              "location": "StepDefinition_Files.DropDown.recliner_for_kids_gets_displayed()"
            },
            "keyword": "Then "
          }
        ],
        "tags": [
          {
            "name": "@Dropdown"
          },
          {
            "name": "@Amazon_Auto_Search"
          }
        ]
      },
      {
        "start_timestamp": "2023-03-26T21:20:02.943Z",
        "line": 17,
        "name": "Autosuggestion_Google",
        "description": "",
        "id": "dropdown-options;autosuggestion-google",
        "after": [
          {
            "result": {
              "error_message": "org.picocontainer.injectors.AbstractInjector$UnsatisfiableDependenciesException: StepDefinition_Files.ScreenshotStepDefs has unsatisfied dependency \u0027interface org.openqa.selenium.WebDriver\u0027 for constructor \u0027public StepDefinition_Files.ScreenshotStepDefs(org.openqa.selenium.WebDriver)\u0027 from org.picocontainer.DefaultPicoContainer@d3f4505:5\u003c|\r\n\tat org.picocontainer.injectors.ConstructorInjector.getGreediestSatisfiableConstructor(ConstructorInjector.java:191)\r\n\tat org.picocontainer.injectors.ConstructorInjector.getGreediestSatisfiableConstructor(ConstructorInjector.java:110)\r\n\tat org.picocontainer.injectors.ConstructorInjector.access$100(ConstructorInjector.java:51)\r\n\tat org.picocontainer.injectors.ConstructorInjector$1.run(ConstructorInjector.java:331)\r\n\tat org.picocontainer.injectors.AbstractInjector$ThreadLocalCyclicDependencyGuard.observe(AbstractInjector.java:270)\r\n\tat org.picocontainer.injectors.ConstructorInjector.getComponentInstance(ConstructorInjector.java:364)\r\n\tat org.picocontainer.injectors.AbstractInjectionFactory$LifecycleAdapter.getComponentInstance(AbstractInjectionFactory.java:56)\r\n\tat org.picocontainer.behaviors.AbstractBehavior.getComponentInstance(AbstractBehavior.java:64)\r\n\tat org.picocontainer.behaviors.Stored.getComponentInstance(Stored.java:91)\r\n\tat org.picocontainer.DefaultPicoContainer.getInstance(DefaultPicoContainer.java:699)\r\n\tat org.picocontainer.DefaultPicoContainer.getComponent(DefaultPicoContainer.java:647)\r\n\tat org.picocontainer.DefaultPicoContainer.getComponent(DefaultPicoContainer.java:678)\r\n\tat io.cucumber.picocontainer.PicoFactory.getInstance(PicoFactory.java:47)\r\n\tat io.cucumber.java.AbstractGlueDefinition.invokeMethod(AbstractGlueDefinition.java:47)\r\n\tat io.cucumber.java.JavaHookDefinition.execute(JavaHookDefinition.java:59)\r\n\tat io.cucumber.core.runner.CoreHookDefinition.execute(CoreHookDefinition.java:46)\r\n\tat io.cucumber.core.runner.HookDefinitionMatch.runStep(HookDefinitionMatch.java:21)\r\n\tat io.cucumber.core.runner.ExecutionMode$1.execute(ExecutionMode.java:10)\r\n\tat io.cucumber.core.runner.TestStep.executeStep(TestStep.java:92)\r\n\tat io.cucumber.core.runner.TestStep.run(TestStep.java:64)\r\n\tat io.cucumber.core.runner.TestCase.run(TestCase.java:110)\r\n\tat io.cucumber.core.runner.Runner.runPickle(Runner.java:73)\r\n\tat io.cucumber.junit.PickleRunners$NoStepDescriptions.run(PickleRunners.java:151)\r\n\tat io.cucumber.junit.FeatureRunner.runChild(FeatureRunner.java:135)\r\n\tat io.cucumber.junit.FeatureRunner.runChild(FeatureRunner.java:27)\r\n\tat org.junit.runners.ParentRunner$3.run(ParentRunner.java:238)\r\n\tat org.junit.runners.ParentRunner$1.schedule(ParentRunner.java:63)\r\n\tat org.junit.runners.ParentRunner.runChildren(ParentRunner.java:236)\r\n\tat org.junit.runners.ParentRunner.access$000(ParentRunner.java:53)\r\n\tat org.junit.runners.ParentRunner$2.evaluate(ParentRunner.java:229)\r\n\tat org.junit.runners.ParentRunner.run(ParentRunner.java:309)\r\n\tat io.cucumber.junit.Cucumber.runChild(Cucumber.java:200)\r\n\tat io.cucumber.junit.Cucumber.runChild(Cucumber.java:90)\r\n\tat org.junit.runners.ParentRunner$3.run(ParentRunner.java:238)\r\n\tat org.junit.runners.ParentRunner$1.schedule(ParentRunner.java:63)\r\n\tat org.junit.runners.ParentRunner.runChildren(ParentRunner.java:236)\r\n\tat org.junit.runners.ParentRunner.access$000(ParentRunner.java:53)\r\n\tat org.junit.runners.ParentRunner$2.evaluate(ParentRunner.java:229)\r\n\tat io.cucumber.junit.Cucumber$RunCucumber.evaluate(Cucumber.java:235)\r\n\tat org.junit.runners.ParentRunner.run(ParentRunner.java:309)\r\n\tat org.eclipse.jdt.internal.junit4.runner.JUnit4TestReference.run(JUnit4TestReference.java:93)\r\n\tat org.eclipse.jdt.internal.junit.runner.TestExecution.run(TestExecution.java:40)\r\n\tat org.eclipse.jdt.internal.junit.runner.RemoteTestRunner.runTests(RemoteTestRunner.java:529)\r\n\tat org.eclipse.jdt.internal.junit.runner.RemoteTestRunner.runTests(RemoteTestRunner.java:756)\r\n\tat org.eclipse.jdt.internal.junit.runner.RemoteTestRunner.run(RemoteTestRunner.java:452)\r\n\tat org.eclipse.jdt.internal.junit.runner.RemoteTestRunner.main(RemoteTestRunner.java:210)\r\n",
              "status": "failed"
            },
            "match": {
              "location": "StepDefinition_Files.ScreenshotStepDefs.afterScenario(io.cucumber.java.Scenario)"
            }
          }
        ],
        "type": "scenario",
        "keyword": "Scenario",
        "steps": [
          {
            "result": {
              "duration": 5558246600,
              "status": "passed"
            },
            "line": 18,
            "name": "I launch chrome and launch google url",
            "match": {
              "location": "StepDefinition_Files.DropDown.i_launch_chrome_and_launch_google_url()"
            },
            "keyword": "Given "
          },
          {
            "result": {
              "duration": 7815918200,
              "status": "passed"
            },
            "line": 19,
            "name": "I enter switzerland Package",
            "match": {
              "location": "StepDefinition_Files.DropDown.i_enter_switzerland_package()"
            },
            "keyword": "When "
          },
          {
            "result": {
              "duration": 1071757100,
              "status": "passed"
            },
            "line": 20,
            "name": "switzerland package option shows in google",
            "match": {
              "location": "StepDefinition_Files.DropDown.switzerland_package_option_shows_in_google()"
            },
            "keyword": "Then "
          }
        ],
        "tags": [
          {
            "name": "@Dropdown"
          },
          {
            "name": "@Googlesearch"
          }
        ]
      }
    ],
    "name": "Dropdown options",
    "description": "",
    "id": "dropdown-options",
    "keyword": "Feature",
    "uri": "file:src/test/resources/Cucumber/DropDown.feature",
    "tags": [
      {
        "name": "@Dropdown",
        "type": "Tag",
        "location": {
          "line": 4,
          "column": 1
        }
      }
    ]
  }
]