[{"line":1,"elements":[{"start_timestamp":"2024-06-13T02:04:47.254Z","line":4,"name":"Compare two BAI2 files","description":"","id":"compare-bai2-files-ignoring-dates;compare-two-bai2-files","type":"scenario","keyword":"Scenario","steps":[{"result":{"duration":7994900,"status":"passed"},"line":5,"name":"I have two BAI2 files \"C:/Users/Admin/Desktop/File_Compare/Actual.txt\" and \"C:/Users/Admin/Desktop/File_Compare/Expected.txt\"","match":{"arguments":[{"val":"\"C:/Users/Admin/Desktop/File_Compare/Actual.txt\"","offset":22},{"val":"\"C:/Users/Admin/Desktop/File_Compare/Expected.txt\"","offset":75}],"location":"StepDefinition_Files.CompareFilesStepDefs.iHaveTwoBAI2Files(java.lang.String,java.lang.String)"},"keyword":"Given "},{"result":{"duration":8995500,"status":"passed"},"line":6,"name":"I compare the files ignoring the dates","match":{"location":"StepDefinition_Files.CompareFilesStepDefs.iCompareTheFilesIgnoringTheDates()"},"keyword":"When "},{"result":{"error_message":"java.lang.AssertionError: Files differ at line 2\r\n\tat org.junit.Assert.fail(Assert.java:89)\r\n\tat StepDefinition_Files.CompareFilesStepDefs.theFilesShouldBeIdentical(CompareFilesStepDefs.java:58)\r\n\tat ✽.the files should be identical(file:///C:/Users/Admin/eclipse-workspace/BDD_CUCUMBER/src/test/resources/Cucumber/Compare%20BAI2%20files%20ignoring%20dates.feature:7)\r\n","duration":12992500,"status":"failed"},"line":7,"name":"the files should be identical","match":{"location":"StepDefinition_Files.CompareFilesStepDefs.theFilesShouldBeIdentical()"},"keyword":"Then "}],"tags":[{"name":"@NotepadVsNotePad"}]}],"name":"Compare BAI2 files ignoring dates","description":"","id":"compare-bai2-files-ignoring-dates","keyword":"Feature","uri":"file:src/test/resources/Cucumber/Compare%20BAI2%20files%20ignoring%20dates.feature","tags":[]}]